actionpi/__init__.py
actionpi/api.py
actionpi/app.py
actionpi/camera.py
actionpi/factory.py
actionpi/gpio.py
actionpi/system.py
actionpi/watchdog.py
actionpi/imp/__init__.py
actionpi/imp/mock.py
actionpi/imp/raspberrypi.py
actionpi/static/.gitignore
actionpi/static/asset-manifest.json
actionpi/static/favicon.ico
actionpi/static/index.html
actionpi/static/logo192.png
actionpi/static/logo512.png
actionpi/static/manifest.json
actionpi/static/precache-manifest.2664c5420b9d670cb4279432c1ac3911.js
actionpi/static/robots.txt
actionpi/static/service-worker.js
actionpi/static/static/css/main.1fc973a9.chunk.css
actionpi/static/static/css/main.1fc973a9.chunk.css.map
actionpi/static/static/js/2.17949a82.chunk.js
actionpi/static/static/js/2.17949a82.chunk.js.LICENSE.txt
actionpi/static/static/js/2.17949a82.chunk.js.map
actionpi/static/static/js/main.5c658155.chunk.js
actionpi/static/static/js/main.5c658155.chunk.js.map
actionpi/static/static/js/runtime-main.c63fbe4a.js
actionpi/static/static/js/runtime-main.c63fbe4a.js.map
actionpi/static/static/media/logo.cabc4b0d.png
actionpi-1.1.17.data/scripts/actionpi
actionpi-1.1.17.dist-info/LICENSE
actionpi-1.1.17.dist-info/METADATA
actionpi-1.1.17.dist-info/WHEEL
actionpi-1.1.17.dist-info/top_level.txt
actionpi-1.1.17.dist-info/RECORD
