Metadata-Version: 2.1
Name: actionpi
Version: 1.1.17
Summary: Action/Dash camera powered by Raspberry Pi Zero
Home-page: https://github.com/andreacioni/actionpi
Author: Andrea Cioni
License: UNKNOWN
Platform: UNKNOWN
Classifier: Programming Language :: Python :: 3
Classifier: License :: OSI Approved :: GNU General Public License v3 (GPLv3)
Classifier: Operating System :: OS Independent
Requires-Dist: pycommon-andreacioni (==0.0.4)
Requires-Dist: flask (==1.1.2)
Requires-Dist: flask-restful (==0.3.8)
Requires-Dist: psutil (==5.7.3)
Requires-Dist: gpiozero (==1.5.1)
Requires-Dist: flask-cors (==3.0.9)
Requires-Dist: picamera (==1.13)
Requires-Dist: RPi.GPIO (==0.7.0)
